ctlconvert/__init__.py
ctlconvert/main.py
ctl_convert-0.0.1.dist-info/METADATA
ctl_convert-0.0.1.dist-info/WHEEL
ctl_convert-0.0.1.dist-info/top_level.txt
ctl_convert-0.0.1.dist-info/RECORD
