Metadata-Version: 2.1
Name: ctl-convert
Version: 0.0.1
Summary: Uzbek Transliterator (Latin - Cyrillic - Latin)
Author: Ziyodulla Abdukarimov
Author-email: ZiyodullaDeveloper@gmail.com
Classifier: Programming Language :: Python :: 3
Classifier: License :: OSI Approved :: MIT License
Classifier: Operating System :: OS Independent
